Workbook

Sheet ANÁLISE DO ROI
A2: CAMPANHAS | B2: INVESTIMENTO | C2: LEADS CAPTADOS | D2: CUSTO POR LEAD | E2: LUCRO | F2: LUCRO SEM PUBLICIDADE | G2: ROI | H2: CÁLCULO DO ROI | I2: % MARGEM DE LUCRO
A3: TRABALHISTA | B3: 880 | C3: 68 | D3: =B3/C3 -> 12.941176 | E3: 8640 | F3: =E3-B3 -> 7760 | G3: =F3/B3 -> 8.8181818 | H3: =G3/100 -> 0.088181818 | I3: =H3*100 -> 8.8181818
A4: PREVIDENCIÁRIO | B4: 1200 | C4: 85 | D4: =B4/C4 -> 14.117647 | E4: 10000 | F4: =E4-B4 -> 8800 | G4: =F4/B4 -> 7.3333333 | H4: =G4/100 -> 0.073333333 | I4: =H4*100 -> 7.3333333
A5: CIVEL | B5: =SUMIF('CONTROLE CLIENTE'!B:B, A5, 'CONTROLE CLIENTE'!E:E) -> 2000 | C5: =SUMIF('CONTROLE CLIENTE'!B:B, A5, 'CONTROLE CLIENTE'!C:C) -> 40 | D5: =B5/C5 -> 50 | E5: 10000 | F5: =E5-B5 -> 8000 | G5: =F5/B5 -> 4 | H5: =G5/100 -> 0.04 | I5: =H5*100 -> 4
A6: GERAL | B6: =SUMIF('CONTROLE CLIENTE'!B:B, A6, 'CONTROLE CLIENTE'!E:E) -> 2000 | C6: =SUMIF('CONTROLE CLIENTE'!B:B, A6, 'CONTROLE CLIENTE'!C:C) -> 40 | D6: =B6/C6 -> 50 | E6: 10000 | F6: =E6-B6 -> 8000 | G6: =F6/B6 -> 4 | H6: =G6/100 -> 0.04 | I6: =H6*100 -> 4
A7: Você pode mensurar o ROI por Campanha ou Grupo de anúncio!

Sheet PREVISIBILIDADE DE VENDAS
A1: CAMPANHAS | B1: CONTATOS RECEBIDOS | C1: PROPOSTAS GERADAS | D1: TX. DE CONVERSÃO CONTATO | E1: VENDAS FECHADAS | F1: TX. DE VENDAS | G1: INV. EM ANÚNCIOS | H1: CUSTO POR VENDA (CAC) | I1: Ticket Média
A2: GERAL | B2: 900 | C2: 850 | D2: =C2/B2 -> 0.94444444 | F2: =E2/C2 -> 0 | G2: ='ANÁLISE DO ROI'!B3 -> 880 | H2: =G2/E2 -> #DIV/0! | I2: 2000
A3: GERAL | B3: 85 | C3: 39 | D3: =C3/B3 -> 0.45882353 | E3: 16 | F3: =E3/C3 -> 0.41025641 | G3: 1100 | H3: =G3/E3 -> 68.75 | I3: 720 | J3: =E3*I3 -> 11520
A4: GERAL | B4: ='ANÁLISE DO ROI'!C5 -> 40 | C4: 15 | D4: =C4/B4 -> 0.375 | E4: 14 | F4: =E4/C4 -> 0.93333333 | G4: ='ANÁLISE DO ROI'!B5 -> 2000 | H4: =G4/E4 -> 142.85714
A5: GERAL | B5: ='ANÁLISE DO ROI'!C6 -> 40 | C5: 20 | D5: =C5/B5 -> 0.5 | E5: 17 | F5: =E5/C5 -> 0.85 | G5: ='ANÁLISE DO ROI'!B6 -> 2000 | H5: =G5/E5 -> 117.64706
B7: Melhorias no Atenidmento
B8: Fluxo de funil de Vendas | C8: Persuasão
B9: Scripts de Atenidmento
B10: Atrenidmento Rápido]

Sheet CONTROLE CLIENTE
A2: Basta Preencher os Valores dos Leads Captados e Conversão que automaticamento o Custo por Lead e Custo por Conversão será calculado
A3: DATA | B3: CAMPANHAS | C3: LEADS CAPTADOS | D3: CONVERSÃO FINAL | E3: VALOR INVESTIDO | F3: CUSTO POR LEAD | G3: CUSTO POR CONVERSÃO
A4: 46023 | B4: TRABALHISTA | C4: 10 | D4: 5 | E4: 500 | F4: =E4/C4 -> 50 | G4: =E4/D4 -> 100
A5: 46023 | B5: PREVIDENCIÁRIO | C5: 10 | D5: 5 | E5: 500 | F5: =E5/C5 -> 50 | G5: =E5/D5 -> 100
A6: 46023 | B6: CIVEL | C6: 10 | D6: 5 | E6: 500 | F6: =E6/C6 -> 50 | G6: =E6/D6 -> 100
A7: 46023 | B7: GERAL | C7: 10 | D7: 5 | E7: 500 | F7: =E7/C7 -> 50 | G7: =E7/D7 -> 100
A8: 46025 | B8: PREVIDENCIÁRIO | C8: 10 | D8: 5 | E8: 500 | F8: =E8/C8 -> 50 | G8: =E8/D8 -> 100
A9: 46025 | B9: TRABALHISTA | C9: 10 | D9: 5 | E9: 500 | F9: =E9/C9 -> 50 | G9: =E9/D9 -> 100
A10: 46026 | B10: TRABALHISTA | C10: 10 | D10: 5 | E10: 500 | F10: =E10/C10 -> 50 | G10: =E10/D10 -> 100
A11: 46027 | B11: PREVIDENCIÁRIO | C11: 10 | D11: 5 | E11: 500 | F11: =E11/C11 -> 50 | G11: =E11/D11 -> 100
A12: 46027 | B12: CIVEL | C12: 10 | D12: 5 | E12: 500 | F12: =E12/C12 -> 50 | G12: =E12/D12 -> 100
A13: 46027 | B13: TRABALHISTA | C13: 10 | D13: 5 | E13: 500 | F13: =E13/C13 -> 50 | G13: =E13/D13 -> 100
A14: 46028 | B14: CIVEL | C14: 10 | D14: 5 | E14: 500 | F14: =E14/C14 -> 50 | G14: =E14/D14 -> 100
A15: 46028 | B15: GERAL | C15: 10 | D15: 5 | E15: 500 | F15: =E15/C15 -> 50 | G15: =E15/D15 -> 100
... A22: 46031 | B22: GERAL | C22: 10 | D22: 5 | E22: 500 | F22: =E22/C22 -> 50 | G22: =E22/D22 -> 100
